st_echarts_events/__init__.py
st_echarts_events/frontend/build/asset-manifest.json
st_echarts_events/frontend/build/bootstrap.min.css
st_echarts_events/frontend/build/index.html
st_echarts_events/frontend/build/precache-manifest.4e70009fb2c2faf7950c024c33519d78.js
st_echarts_events/frontend/build/service-worker.js
st_echarts_events/frontend/build/static/js/2.9205fdfb.chunk.js
st_echarts_events/frontend/build/static/js/2.9205fdfb.chunk.js.LICENSE.txt
st_echarts_events/frontend/build/static/js/2.9205fdfb.chunk.js.map
st_echarts_events/frontend/build/static/js/main.e0a2b715.chunk.js
st_echarts_events/frontend/build/static/js/main.e0a2b715.chunk.js.map
st_echarts_events/frontend/build/static/js/runtime-main.c97481d4.js
st_echarts_events/frontend/build/static/js/runtime-main.c97481d4.js.map
st_echarts_events-1.0.0.dist-info/LICENSE
st_echarts_events-1.0.0.dist-info/METADATA
st_echarts_events-1.0.0.dist-info/WHEEL
st_echarts_events-1.0.0.dist-info/top_level.txt
st_echarts_events-1.0.0.dist-info/RECORD
