Metadata-Version: 2.1
Name: st-echarts-events
Version: 1.0.0
Summary: A custom streamlit component to return echarts events values to streamlit
Home-page: UNKNOWN
Author: 隐园
Author-email: brightxml@gmail.com
License: UNKNOWN
Platform: UNKNOWN
Requires-Python: >=3.6
Requires-Dist: streamlit (>=0.63)
